LICENSE
README.md
setup.py
Plost.egg-info/PKG-INFO
Plost.egg-info/SOURCES.txt
Plost.egg-info/dependency_links.txt
Plost.egg-info/top_level.txt
plost/__init__.py