Metadata-Version: 2.1
Name: Plost
Version: 0.2.0
Summary: A deceptively simple plotting library for Streamlit
Home-page: https://github.com/tvst/plost
Author: Thiago Teixeira
Author-email: me@thiagot.com
License: Apache 2
Platform: UNKNOWN
Classifier: Programming Language :: Python :: 3
Classifier: License :: OSI Approved :: Apache Software License
Classifier: Operating System :: OS Independent
Requires-Python: >=3.5
